{
  "id_nortag": "1099364961",
  "index_page": 0,
  "name_nortag": "Yukino Yukinoshita",
  "total_img": 30,
  "total_page": 0,
  "hc_lt_alb": "282185619",
  "hc_lt_data_img": "-207630417",
  "hc_lt_nortag": "-742850542",
  "hc_lt_sptag": "-1979589145",
  "lt_alb": [
    {
      "id_alb": "2024260576",
      "name_alb": "Couple",
      "total_img": 2059
    },
    {
      "id_alb": "-892807948",
      "name_alb": "Crossover",
      "total_img": 505
    },
    {
      "id_alb": "68811063",
      "name_alb": "Girls",
      "total_img": 68557
    },
    {
      "id_alb": "-1741349685",
      "name_alb": "My Teen Romantic Comedy SNAFU",
      "total_img": 49
    },
    {
      "id_alb": "109656519",
      "name_alb": "Original 6",
      "total_img": 437
    }
  ],
  "lt_data_img": [
    {
      "hc_lt_id_alb": "944333569",
      "hc_lt_id_nortag": "96561207",
      "hc_lt_id_sptag": "",
      "id_img": "Crossover_833321_crop2608_2087568027",
      "link_img": "UTb0sGqADnbLiHq9qhRMRkSRiLND0Tk7ctN8tpraiifDtSIUWB5eoaRJ1CGkPk1q5FSGQG6LUcO2g1znHXbhu5Vy4706IhQgSYlgwrgVRHU=",
      "thumb": "UTb0sGqADnbLiHq9qhRMRkSRiLND0Tk7ctN8tpraiifDtSIUWB5eoaRJ1CGkPk1qtJ/qLW6ZW35swcKWM4yrsZVy4706IhQgSYlgwrgVRHU=",
      "lt_id_alb": [
        "-892807948"
      ],
      "list_id_nortag": [
        "455752626",
        "1837763930",
        "-1361231934",
        "-540557569",
        "-148568472",
        "-958187632",
        "-899970271",
        "518491969",
        "489708789",
        "-890365842",
        "-711817417",
        "584016335",
        "1862163858",
        "-1278041944",
        "1182614953",
        "570659319",
        "-1873931185",
        "436735501",
        "2225266",
        "-1185956769",
        "-63719044",
        "-114492302",
        "554120321",
        "-1769491654",
        "115056883",
        "940301965",
        "-928006557",
        "-320799925",
        "-182895206",
        "-285202530",
        "-1352771606",
        "1869358694",
        "1339700914",
        "-342064395",
        "-1643022489",
        "-61413949",
        "-272046484",
        "-455647535",
        "-460280087",
        "2115335358",
        "1684926246",
        "-759650044",
        "1099364961",
        "-979079592",
        "1701816780",
        "-339618269",
        "-2066368222",
        "154658675",
        "-1611763306",
        "-455869487"
      ]
    },
    {
      "hc_lt_id_alb": "433290349",
      "hc_lt_id_nortag": "-782089407",
      "hc_lt_id_sptag": "490411586",
      "id_img": "MyTeenRomanticComedySNAFU_710656_crop2608_41217197",
      "link_img": "UTb0sGqADnbLiHq9qhRMRkSRiLND0Tk7ctN8tpraiidpMeGle4dd1GX/cEVhNo2X+YOH7Ylb4Zj8rAuPBZBT0ZVy4706IhQgSYlgwrgVRHU=",
      "thumb": "UTb0sGqADnbLiHq9qhRMRkSRiLND0Tk7ctN8tpraiidpMeGle4dd1GX/cEVhNo2X+JscnNezqs3DSejnyMLuy5Vy4706IhQgSYlgwrgVRHU=",
      "lt_id_alb": [
        "-1741349685",
        "68811063"
      ],
      "list_id_nortag": [
        "1099364961"
      ],
      "lt_id_sptag": [
        "-154622774",
        "891390002",
        "-369654561",
        "-1436512555",
        "82870",
        "126637389",
        "-326078627",
        "1439506876",
        "-1783086774",
        "1911583362"
      ]
    },
    {
      "hc_lt_id_alb": "433290349",
      "hc_lt_id_nortag": "1456337921",
      "hc_lt_id_sptag": "-874528341",
      "id_img": "MyTeenRomanticComedySNAFU_736333_crop2608_1985166438",
      "link_img": "UTb0sGqADnbLiHq9qhRMRkSRiLND0Tk7ctN8tpraiieSP5+nTOA+StUE9oGBfBJQMoHP2+NQRIMxQlrQHOCyTZVy4706IhQgSYlgwrgVRHU=",
      "thumb": "UTb0sGqADnbLiHq9qhRMRkSRiLND0Tk7ctN8tpraiieSP5+nTOA+StUE9oGBfBJQCn6Jq43M3F7qb9SgBr7VT5Vy4706IhQgSYlgwrgVRHU=",
      "lt_id_alb": [
        "-1741349685",
        "68811063"
      ],
      "list_id_nortag": [
        "2015789921",
        "1099364961"
      ],
      "lt_id_sptag": [
        "-154622774",
        "891390002",
        "82870",
        "126637389",
        "-326078627",
        "1911583362",
        "635218351"
      ]
    },
    {
      "hc_lt_id_alb": "433290349",
      "hc_lt_id_nortag": "1456337921",
      "hc_lt_id_sptag": "-1744468379",
      "id_img": "MyTeenRomanticComedySNAFU_713047_crop2608_121534694",
      "link_img": "UTb0sGqADnbLiHq9qhRMRkSRiLND0Tk7ctN8tpraiieyHrWkRhnugvDTpNcEkKb6zuunqC4ssmH5PxaVsfXXbpVy4706IhQgSYlgwrgVRHU=",
      "thumb": "UTb0sGqADnbLiHq9qhRMRkSRiLND0Tk7ctN8tpraiieyHrWkRhnugvDTpNcEkKb6BbJGtY6Ldt/ThM7uyWd+spVy4706IhQgSYlgwrgVRHU=",
      "lt_id_alb": [
        "-1741349685",
        "68811063"
      ],
      "list_id_nortag": [
        "2015789921",
        "1099364961"
      ],
      "lt_id_sptag": [
        "-154622774",
        "-120608061",
        "891390002",
        "-2139213873",
        "82870",
        "126637389",
        "-326078627",
        "1439506876",
        "-1783086774",
        "1911583362"
      ]
    },
    {
      "hc_lt_id_alb": "433290349",
      "hc_lt_id_nortag": "1456337921",
      "hc_lt_id_sptag": "667133582",
      "id_img": "MyTeenRomanticComedySNAFU_875151_crop2608_-1342361629",
      "link_img": "UTb0sGqADnbLiHq9qhRMRkSRiLND0Tk7ctN8tpraiidRStrg3+lB47BtmfYX7QGW8Q8QkfV8X5c4XHip7Hwr5pVy4706IhQgSYlgwrgVRHU=",
      "thumb": "UTb0sGqADnbLiHq9qhRMRkSRiLND0Tk7ctN8tpraiidRStrg3+lB47BtmfYX7QGWtzdEfKHbE0PVU9hpnsTAW5Vy4706IhQgSYlgwrgVRHU=",
      "lt_id_alb": [
        "-1741349685",
        "68811063"
      ],
      "list_id_nortag": [
        "2015789921",
        "1099364961"
      ],
      "lt_id_sptag": [
        "-154622774",
        "891390002",
        "-2139213873",
        "-143120565",
        "-326078627",
        "1129122964",
        "1911583362",
        "635218351"
      ]
    },
    {
      "hc_lt_id_alb": "944333569",
      "hc_lt_id_nortag": "96561207",
      "hc_lt_id_sptag": "",
      "id_img": "Crossover_833321_crop2608_-1885622569",
      "link_img": "UTb0sGqADnbLiHq9qhRMRkSRiLND0Tk7ctN8tpraiidrW9lfTpS8oKFMYNC3ExANB9xZ65Xih3gOkeyhHiu555Vy4706IhQgSYlgwrgVRHU=",
      "thumb": "UTb0sGqADnbLiHq9qhRMRkSRiLND0Tk7ctN8tpraiidrW9lfTpS8oKFMYNC3ExANFQu8rS4xS6He48hthWwWJ5Vy4706IhQgSYlgwrgVRHU=",
      "lt_id_alb": [
        "-892807948"
      ],
      "list_id_nortag": [
        "455752626",
        "1837763930",
        "-1361231934",
        "-540557569",
        "-148568472",
        "-958187632",
        "-899970271",
        "518491969",
        "489708789",
        "-890365842",
        "-711817417",
        "584016335",
        "1862163858",
        "-1278041944",
        "1182614953",
        "570659319",
        "-1873931185",
        "436735501",
        "2225266",
        "-1185956769",
        "-63719044",
        "-114492302",
        "554120321",
        "-1769491654",
        "115056883",
        "940301965",
        "-928006557",
        "-320799925",
        "-182895206",
        "-285202530",
        "-1352771606",
        "1869358694",
        "1339700914",
        "-342064395",
        "-1643022489",
        "-61413949",
        "-272046484",
        "-455647535",
        "-460280087",
        "2115335358",
        "1684926246",
        "-759650044",
        "1099364961",
        "-979079592",
        "1701816780",
        "-339618269",
        "-2066368222",
        "154658675",
        "-1611763306",
        "-455869487"
      ]
    },
    {
      "hc_lt_id_alb": "433290349",
      "hc_lt_id_nortag": "-782089407",
      "hc_lt_id_sptag": "-1179765881",
      "id_img": "MyTeenRomanticComedySNAFU_753145_crop2608_-622496279",
      "link_img": "UTb0sGqADnbLiHq9qhRMRkSRiLND0Tk7ctN8tpraiifQYZKueBZbSuEj5wSdugnOKCE1KoQeESTzQCYAOqRB3ZVy4706IhQgSYlgwrgVRHU=",
      "thumb": "UTb0sGqADnbLiHq9qhRMRkSRiLND0Tk7ctN8tpraiifQYZKueBZbSuEj5wSdugnOLshiivVc3gV0fDsj5jYccJVy4706IhQgSYlgwrgVRHU=",
      "lt_id_alb": [
        "-1741349685",
        "68811063"
      ],
      "list_id_nortag": [
        "1099364961"
      ],
      "lt_id_sptag": [
        "-154622774",
        "891390002",
        "-1782893951",
        "-326078627",
        "635372596",
        "1911583362"
      ]
    },
    {
      "hc_lt_id_alb": "433290349",
      "hc_lt_id_nortag": "-980895501",
      "hc_lt_id_sptag": "-1663941938",
      "id_img": "MyTeenRomanticComedySNAFU_586391_crop2608_-1357726300",
      "link_img": "UTb0sGqADnbLiHq9qhRMRkSRiLND0Tk7ctN8tpraiieTDyizTPvxqedBNtmysBKhx+NOGsrw+JYD0BvPSGRI5ZVy4706IhQgSYlgwrgVRHU=",
      "thumb": "UTb0sGqADnbLiHq9qhRMRkSRiLND0Tk7ctN8tpraiieTDyizTPvxqedBNtmysBKh3F0CGSgFot/Yb6wurBjDg5Vy4706IhQgSYlgwrgVRHU=",
      "lt_id_alb": [
        "-1741349685",
        "68811063"
      ],
      "list_id_nortag": [
        "67510",
        "1099364961",
        "-303857400"
      ],
      "lt_id_sptag": [
        "-154622774",
        "891390002",
        "-143380300",
        "-326078627",
        "635372596",
        "-1783086774",
        "1911583362"
      ]
    },
    {
      "hc_lt_id_alb": "433290349",
      "hc_lt_id_nortag": "1456337921",
      "hc_lt_id_sptag": "-2139815608",
      "id_img": "MyTeenRomanticComedySNAFU_736334_crop2608_1985167398",
      "link_img": "UTb0sGqADnbLiHq9qhRMRkSRiLND0Tk7ctN8tpraiifXdFbB4DmJKvIGV30wdJ3CmR21G3yASIhnLZua+t4f4ZVy4706IhQgSYlgwrgVRHU=",
      "thumb": "UTb0sGqADnbLiHq9qhRMRkSRiLND0Tk7ctN8tpraiifXdFbB4DmJKvIGV30wdJ3C7EdZlscDDvqPijtRX0XWXpVy4706IhQgSYlgwrgVRHU=",
      "lt_id_alb": [
        "-1741349685",
        "68811063"
      ],
      "list_id_nortag": [
        "2015789921",
        "1099364961"
      ],
      "lt_id_sptag": [
        "-154622774",
        "936615491",
        "635632331",
        "-2139213873",
        "-143120565",
        "82870",
        "-1364967268",
        "126637389",
        "-326078627",
        "-369386728",
        "-143162340",
        "1911583362",
        "635218351"
      ]
    },
    {
      "hc_lt_id_alb": "433290349",
      "hc_lt_id_nortag": "1887471195",
      "hc_lt_id_sptag": "-430495677",
      "id_img": "MyTeenRomanticComedySNAFU_717273_crop2608_237983869",
      "link_img": "UTb0sGqADnbLiHq9qhRMRkSRiLND0Tk7ctN8tpraiid7jHIKEXyKI5Z+/+BFB2mWPFFYaewmx4p+o4MrPJ5mgJVy4706IhQgSYlgwrgVRHU=",
      "thumb": "UTb0sGqADnbLiHq9qhRMRkSRiLND0Tk7ctN8tpraiid7jHIKEXyKI5Z+/+BFB2mWVnlOGCVTKQYlHaOiHe5kRZVy4706IhQgSYlgwrgVRHU=",
      "lt_id_alb": [
        "-1741349685",
        "68811063"
      ],
      "list_id_nortag": [
        "1433810066",
        "2015789921",
        "1099364961"
      ],
      "lt_id_sptag": [
        "-154622774",
        "891390002",
        "-2139213873",
        "-143120565",
        "82870",
        "-1782893951",
        "-143380300",
        "126637389",
        "-326078627",
        "635372596",
        "1439812287",
        "-1783086774",
        "1911583362",
        "-143528947"
      ]
    },
    {
      "hc_lt_id_alb": "944333569",
      "hc_lt_id_nortag": "96561207",
      "hc_lt_id_sptag": "",
      "id_img": "Crossover_833321_crop2608_702636650",
      "link_img": "UTb0sGqADnbLiHq9qhRMRkSRiLND0Tk7ctN8tpraiifJQSkRwqaE09C9tAwhw8d4uKKZi8Bq2PjYM1wDIfP2oZVy4706IhQgSYlgwrgVRHU=",
      "thumb": "UTb0sGqADnbLiHq9qhRMRkSRiLND0Tk7ctN8tpraiifJQSkRwqaE09C9tAwhw8d48F6B0hfNJPIxkcEqZixfO5Vy4706IhQgSYlgwrgVRHU=",
      "lt_id_alb": [
        "-892807948"
      ],
      "list_id_nortag": [
        "455752626",
        "1837763930",
        "-1361231934",
        "-540557569",
        "-148568472",
        "-958187632",
        "-899970271",
        "518491969",
        "489708789",
        "-890365842",
        "-711817417",
        "584016335",
        "1862163858",
        "-1278041944",
        "1182614953",
        "570659319",
        "-1873931185",
        "436735501",
        "2225266",
        "-1185956769",
        "-63719044",
        "-114492302",
        "554120321",
        "-1769491654",
        "115056883",
        "940301965",
        "-928006557",
        "-320799925",
        "-182895206",
        "-285202530",
        "-1352771606",
        "1869358694",
        "1339700914",
        "-342064395",
        "-1643022489",
        "-61413949",
        "-272046484",
        "-455647535",
        "-460280087",
        "2115335358",
        "1684926246",
        "-759650044",
        "1099364961",
        "-979079592",
        "1701816780",
        "-339618269",
        "-2066368222",
        "154658675",
        "-1611763306",
        "-455869487"
      ]
    },
    {
      "hc_lt_id_alb": "535544958",
      "hc_lt_id_nortag": "1153877818",
      "hc_lt_id_sptag": "",
      "id_img": "MyTeenRomanticComedySNAFU_599322_crop2608_-384542741",
      "link_img": "UTb0sGqADnbLiHq9qhRMRkSRiLND0Tk7ctN8tpraiidvpdr1o9GAf0lCua4pBMeViiqIAiTey3erBp9jxJl/qZVy4706IhQgSYlgwrgVRHU=",
      "thumb": "UTb0sGqADnbLiHq9qhRMRkSRiLND0Tk7ctN8tpraiidvpdr1o9GAf0lCua4pBMeVhLjivmMX325ziMBY4qqNMpVy4706IhQgSYlgwrgVRHU=",
      "lt_id_alb": [
        "-1741349685",
        "2024260576"
      ],
      "list_id_nortag": [
        "1433810066",
        "1207255719",
        "2015789921",
        "1099364961"
      ]
    },
    {
      "hc_lt_id_alb": "433290349",
      "hc_lt_id_nortag": "-782089407",
      "hc_lt_id_sptag": "-340128198",
      "id_img": "MyTeenRomanticComedySNAFU_895082_crop2608_431812546",
      "link_img": "UTb0sGqADnbLiHq9qhRMRkSRiLND0Tk7ctN8tpraiicsn3HiwXdwwjY8fdQnqqYIYEUQsdIi7596ggBYYqXIhJVy4706IhQgSYlgwrgVRHU=",
      "thumb": "UTb0sGqADnbLiHq9qhRMRkSRiLND0Tk7ctN8tpraiicsn3HiwXdwwjY8fdQnqqYIgM/n/xpG0r7aDcZfJoDSkJVy4706IhQgSYlgwrgVRHU=",
      "lt_id_alb": [
        "-1741349685",
        "68811063"
      ],
      "list_id_nortag": [
        "1099364961"
      ],
      "lt_id_sptag": [
        "-1811357781",
        "-1415763167",
        "-326078627",
        "-143534545",
        "1911583362",
        "635218351"
      ]
    },
    {
      "hc_lt_id_alb": "433290349",
      "hc_lt_id_nortag": "1887471195",
      "hc_lt_id_sptag": "50414073",
      "id_img": "MyTeenRomanticComedySNAFU_694177_crop2608_1213428556",
      "link_img": "UTb0sGqADnbLiHq9qhRMRkSRiLND0Tk7ctN8tpraiieejluZtGjQt1y9rat4iCLm9Kdv6ohOKzt2Rsd35no93JVy4706IhQgSYlgwrgVRHU=",
      "thumb": "UTb0sGqADnbLiHq9qhRMRkSRiLND0Tk7ctN8tpraiieejluZtGjQt1y9rat4iCLmhOG43GJqSAQONqw/aTfxhZVy4706IhQgSYlgwrgVRHU=",
      "lt_id_alb": [
        "-1741349685",
        "68811063"
      ],
      "list_id_nortag": [
        "1433810066",
        "2015789921",
        "1099364961"
      ],
      "lt_id_sptag": [
        "-154622774",
        "891390002",
        "82870",
        "126637389",
        "-326078627",
        "1911583362",
        "635218351",
        "-143528947"
      ]
    },
    {
      "hc_lt_id_alb": "535544958",
      "hc_lt_id_nortag": "1887471195",
      "hc_lt_id_sptag": "",
      "id_img": "MyTeenRomanticComedySNAFU_694177_crop2608_1213428557",
      "link_img": "UTb0sGqADnbLiHq9qhRMRkSRiLND0Tk7ctN8tpraiifbIrhcbNWM+jUYYosNkOt/K//bnQDOSodGYg3c9sPawpVy4706IhQgSYlgwrgVRHU=",
      "thumb": "UTb0sGqADnbLiHq9qhRMRkSRiLND0Tk7ctN8tpraiifbIrhcbNWM+jUYYosNkOt/Prcu4najuLW3Ktpgfs5uIJVy4706IhQgSYlgwrgVRHU=",
      "lt_id_alb": [
        "-1741349685",
        "2024260576"
      ],
      "list_id_nortag": [
        "1433810066",
        "2015789921",
        "1099364961"
      ]
    },
    {
      "hc_lt_id_alb": "433290349",
      "hc_lt_id_nortag": "1456337921",
      "hc_lt_id_sptag": "-1929820394",
      "id_img": "MyTeenRomanticComedySNAFU_736333_crop2608_1985166437",
      "link_img": "UTb0sGqADnbLiHq9qhRMRkSRiLND0Tk7ctN8tpraiid/iSITfWKFGhxOmPqUP4VvwSqDRYPlQspP3/G2prfy65Vy4706IhQgSYlgwrgVRHU=",
      "thumb": "UTb0sGqADnbLiHq9qhRMRkSRiLND0Tk7ctN8tpraiid/iSITfWKFGhxOmPqUP4VvsdFgo2OltHDlU7EA7EaVkpVy4706IhQgSYlgwrgVRHU=",
      "lt_id_alb": [
        "-1741349685",
        "68811063"
      ],
      "list_id_nortag": [
        "2015789921",
        "1099364961"
      ],
      "lt_id_sptag": [
        "891390002",
        "-2139213873",
        "-143120565",
        "82870",
        "-1364967268",
        "126637389",
        "1600730941",
        "-143162340",
        "1439812287",
        "1911583362"
      ]
    },
    {
      "hc_lt_id_alb": "433290349",
      "hc_lt_id_nortag": "1887471195",
      "hc_lt_id_sptag": "561876264",
      "id_img": "MyTeenRomanticComedySNAFU_717270_crop2608_237980986",
      "link_img": "UTb0sGqADnbLiHq9qhRMRkSRiLND0Tk7ctN8tpraiic591xn5RyPk9oEur1EW8W9m77n6JH27lB9HL4UmE/wx5Vy4706IhQgSYlgwrgVRHU=",
      "thumb": "UTb0sGqADnbLiHq9qhRMRkSRiLND0Tk7ctN8tpraiic591xn5RyPk9oEur1EW8W9WatCgzLPtHoEP03muiD6eJVy4706IhQgSYlgwrgVRHU=",
      "lt_id_alb": [
        "-1741349685",
        "68811063"
      ],
      "list_id_nortag": [
        "1433810066",
        "2015789921",
        "1099364961"
      ],
      "lt_id_sptag": [
        "-154622774",
        "-120608061",
        "1043155746",
        "891390002",
        "154003721",
        "-2139213873",
        "-326078627",
        "1434519004",
        "635372596",
        "-1783086774",
        "1911583362"
      ]
    },
    {
      "hc_lt_id_alb": "433290349",
      "hc_lt_id_nortag": "-782089407",
      "hc_lt_id_sptag": "-1069154263",
      "id_img": "MyTeenRomanticComedySNAFU_736348_crop2608_1985201033",
      "link_img": "UTb0sGqADnbLiHq9qhRMRkSRiLND0Tk7ctN8tpraiic5NxyKT2Cb46lyH+S1kUdFkTAGS/T2M0PEWYSgHvQgHJVy4706IhQgSYlgwrgVRHU=",
      "thumb": "UTb0sGqADnbLiHq9qhRMRkSRiLND0Tk7ctN8tpraiic5NxyKT2Cb46lyH+S1kUdFlGY1DwKO34fehn8w/xWXHJVy4706IhQgSYlgwrgVRHU=",
      "lt_id_alb": [
        "-1741349685",
        "68811063"
      ],
      "list_id_nortag": [
        "1099364961"
      ],
      "lt_id_sptag": [
        "-154622774",
        "891390002",
        "-369654561",
        "-1436512555",
        "82870",
        "126637389",
        "-326078627",
        "-1783086774",
        "1911583362"
      ]
    },
    {
      "hc_lt_id_alb": "433290349",
      "hc_lt_id_nortag": "1456337921",
      "hc_lt_id_sptag": "-974317713",
      "id_img": "MyTeenRomanticComedySNAFU_736355_crop2608_-379190203",
      "link_img": "UTb0sGqADnbLiHq9qhRMRkSRiLND0Tk7ctN8tpraiifCvjzZ+Yw7qmRdUnYjbecBeZhLx/mC26WHdJ1UjbHz3ZVy4706IhQgSYlgwrgVRHU=",
      "thumb": "UTb0sGqADnbLiHq9qhRMRkSRiLND0Tk7ctN8tpraiifCvjzZ+Yw7qmRdUnYjbecBMRXw5TCsmTEJkU8XfzejG5Vy4706IhQgSYlgwrgVRHU=",
      "lt_id_alb": [
        "-1741349685",
        "68811063"
      ],
      "list_id_nortag": [
        "2015789921",
        "1099364961"
      ],
      "lt_id_sptag": [
        "-154622774",
        "891390002",
        "-2139213873",
        "-143120565",
        "-1364967268",
        "-326078627",
        "-143534545",
        "1911583362",
        "635218351"
      ]
    },
    {
      "hc_lt_id_alb": "433290349",
      "hc_lt_id_nortag": "-782089407",
      "hc_lt_id_sptag": "2082433577",
      "id_img": "MyTeenRomanticComedySNAFU_721827_crop2608_959108659",
      "link_img": "UTb0sGqADnbLiHq9qhRMRkSRiLND0Tk7ctN8tpraiidGOASD1AXooXVaI4+hdptjeihEkqshUpyeIM3ZOjhqGpVy4706IhQgSYlgwrgVRHU=",
      "thumb": "UTb0sGqADnbLiHq9qhRMRkSRiLND0Tk7ctN8tpraiidGOASD1AXooXVaI4+hdptjearKN/gEewED5ereOd36kJVy4706IhQgSYlgwrgVRHU=",
      "lt_id_alb": [
        "-1741349685",
        "68811063"
      ],
      "list_id_nortag": [
        "1099364961"
      ],
      "lt_id_sptag": [
        "-154622774",
        "891390002",
        "82870",
        "-1782893951",
        "126637389",
        "-326078627",
        "-1783086774",
        "1911583362"
      ]
    },
    {
      "hc_lt_id_alb": "433290349",
      "hc_lt_id_nortag": "-782089407",
      "hc_lt_id_sptag": "-898651490",
      "id_img": "MyTeenRomanticComedySNAFU_896813_crop2608_467622289",
      "link_img": "UTb0sGqADnbLiHq9qhRMRkSRiLND0Tk7ctN8tpraiidm9RiPHmlmeetf4meJ3vWX5vJa44NoA5UKKZTy63Nn/pVy4706IhQgSYlgwrgVRHU=",
      "thumb": "UTb0sGqADnbLiHq9qhRMRkSRiLND0Tk7ctN8tpraiidm9RiPHmlmeetf4meJ3vWXrWs15AOfpLOh4NfyExdBopVy4706IhQgSYlgwrgVRHU=",
      "lt_id_alb": [
        "-1741349685",
        "68811063"
      ],
      "list_id_nortag": [
        "1099364961"
      ],
      "lt_id_sptag": [
        "-154622774",
        "891390002",
        "-326078627",
        "1600730941",
        "-1783086774",
        "1911583362"
      ]
    },
    {
      "hc_lt_id_alb": "433290349",
      "hc_lt_id_nortag": "1456337921",
      "hc_lt_id_sptag": "1512032989",
      "id_img": "MyTeenRomanticComedySNAFU_736359_crop2608_1985231786",
      "link_img": "UTb0sGqADnbLiHq9qhRMRkSRiLND0Tk7ctN8tpraiicAr1UNF/kq3a79+Jogm0eKPIhUkC1CB86B6ONL8Yw8aJVy4706IhQgSYlgwrgVRHU=",
      "thumb": "UTb0sGqADnbLiHq9qhRMRkSRiLND0Tk7ctN8tpraiicAr1UNF/kq3a79+Jogm0eKnBCU1pxKWY+48VIHxn9uTJVy4706IhQgSYlgwrgVRHU=",
      "lt_id_alb": [
        "-1741349685",
        "68811063"
      ],
      "list_id_nortag": [
        "2015789921",
        "1099364961"
      ],
      "lt_id_sptag": [
        "-120608061",
        "891390002",
        "-2139213873",
        "1434519004",
        "-143162340",
        "1439812287",
        "1439506876",
        "1911583362",
        "635218351"
      ]
    },
    {
      "hc_lt_id_alb": "433290349",
      "hc_lt_id_nortag": "-782089407",
      "hc_lt_id_sptag": "-537642893",
      "id_img": "MyTeenRomanticComedySNAFU_745096_crop2608_-1453515263",
      "link_img": "UTb0sGqADnbLiHq9qhRMRkSRiLND0Tk7ctN8tpraiifIrYqbjI/rvmx343hmfESaFICFwttZzeiaR64JNurhv5Vy4706IhQgSYlgwrgVRHU=",
      "thumb": "UTb0sGqADnbLiHq9qhRMRkSRiLND0Tk7ctN8tpraiifIrYqbjI/rvmx343hmfESam7YQPJPnatYiZ+fCfsOs35Vy4706IhQgSYlgwrgVRHU=",
      "lt_id_alb": [
        "-1741349685",
        "68811063"
      ],
      "list_id_nortag": [
        "1099364961"
      ],
      "lt_id_sptag": [
        "-154622774",
        "891390002",
        "82870",
        "126637389",
        "-326078627",
        "-1743477818",
        "1439506876",
        "1911583362",
        "635218351"
      ]
    },
    {
      "hc_lt_id_alb": "433290349",
      "hc_lt_id_nortag": "1456337921",
      "hc_lt_id_sptag": "-1020405562",
      "id_img": "MyTeenRomanticComedySNAFU_633120_crop2608_755467283",
      "link_img": "UTb0sGqADnbLiHq9qhRMRkSRiLND0Tk7ctN8tpraiicJtBfeU1Ohyp+W2xBhTfCtcbltFkH5YjnyYNMzhwzhSZVy4706IhQgSYlgwrgVRHU=",
      "thumb": "UTb0sGqADnbLiHq9qhRMRkSRiLND0Tk7ctN8tpraiicJtBfeU1Ohyp+W2xBhTfCtJMKwxoUrOM8bb869Ad7THpVy4706IhQgSYlgwrgVRHU=",
      "lt_id_alb": [
        "-1741349685",
        "68811063"
      ],
      "list_id_nortag": [
        "2015789921",
        "1099364961"
      ],
      "lt_id_sptag": [
        "-154622774",
        "936615491",
        "891390002",
        "-2139213873",
        "-143120565",
        "-1364967268",
        "-326078627",
        "71899412",
        "1439812287",
        "1911583362",
        "635218351",
        "-143528947"
      ]
    },
    {
      "hc_lt_id_alb": "433290349",
      "hc_lt_id_nortag": "-782089407",
      "hc_lt_id_sptag": "490411586",
      "id_img": "MyTeenRomanticComedySNAFU_723892_crop2608_1016570693",
      "link_img": "UTb0sGqADnbLiHq9qhRMRkSRiLND0Tk7ctN8tpraiieJokQOyNjxtw2EuhS1IQTp6uTOXOsmpun7vrgAimJ7TpVy4706IhQgSYlgwrgVRHU=",
      "thumb": "UTb0sGqADnbLiHq9qhRMRkSRiLND0Tk7ctN8tpraiieJokQOyNjxtw2EuhS1IQTpqTRahMdkoGwH5FFO8lFqcJVy4706IhQgSYlgwrgVRHU=",
      "lt_id_alb": [
        "-1741349685",
        "68811063"
      ],
      "list_id_nortag": [
        "1099364961"
      ],
      "lt_id_sptag": [
        "-154622774",
        "891390002",
        "-369654561",
        "-1436512555",
        "82870",
        "126637389",
        "-326078627",
        "1439506876",
        "-1783086774",
        "1911583362"
      ]
    },
    {
      "hc_lt_id_alb": "433290349",
      "hc_lt_id_nortag": "1456337921",
      "hc_lt_id_sptag": "1484440712",
      "id_img": "MyTeenRomanticComedySNAFU_736359_crop2608_1985231785",
      "link_img": "UTb0sGqADnbLiHq9qhRMRkSRiLND0Tk7ctN8tpraiidPpMv1uBOWPkctV+YOHHRIVeO3xm0Ed2UocbuN7+F9upVy4706IhQgSYlgwrgVRHU=",
      "thumb": "UTb0sGqADnbLiHq9qhRMRkSRiLND0Tk7ctN8tpraiidPpMv1uBOWPkctV+YOHHRIrDYlsTAL2ZN7jxf45iMxspVy4706IhQgSYlgwrgVRHU=",
      "lt_id_alb": [
        "-1741349685",
        "68811063"
      ],
      "list_id_nortag": [
        "2015789921",
        "1099364961"
      ],
      "lt_id_sptag": [
        "-154622774",
        "891390002",
        "-326078627",
        "1129122964",
        "71899412",
        "1439506876",
        "1911583362"
      ]
    },
    {
      "hc_lt_id_alb": "433290349",
      "hc_lt_id_nortag": "-782089407",
      "hc_lt_id_sptag": "2072064033",
      "id_img": "MyTeenRomanticComedySNAFU_703244_crop2608_-764124828",
      "link_img": "UTb0sGqADnbLiHq9qhRMRkSRiLND0Tk7ctN8tpraiicY6a9BavvP6nocfW248Esx2ooKvpF0ekW8SEa4B8Ay2ZVy4706IhQgSYlgwrgVRHU=",
      "thumb": "UTb0sGqADnbLiHq9qhRMRkSRiLND0Tk7ctN8tpraiicY6a9BavvP6nocfW248EsxS4AwgqC74UKeRJZ3aYnpYJVy4706IhQgSYlgwrgVRHU=",
      "lt_id_alb": [
        "-1741349685",
        "68811063"
      ],
      "list_id_nortag": [
        "1099364961"
      ],
      "lt_id_sptag": [
        "-154622774",
        "82870",
        "126637389",
        "-326078627",
        "-369535327",
        "-1783086774",
        "1911583362"
      ]
    },
    {
      "hc_lt_id_alb": "433290349",
      "hc_lt_id_nortag": "-1847362796",
      "hc_lt_id_sptag": "-204153481",
      "id_img": "MyTeenRomanticComedySNAFU_658268_crop2608_-994642873",
      "link_img": "UTb0sGqADnbLiHq9qhRMRkSRiLND0Tk7ctN8tpraiifxK1VInlSddO8g/Gbx5ST4pYMJNhbFiXK0IXsebpkKeZVy4706IhQgSYlgwrgVRHU=",
      "thumb": "UTb0sGqADnbLiHq9qhRMRkSRiLND0Tk7ctN8tpraiifxK1VInlSddO8g/Gbx5ST447pMalv3TTdRvfXDFLIG/JVy4706IhQgSYlgwrgVRHU=",
      "lt_id_alb": [
        "-1741349685",
        "68811063"
      ],
      "list_id_nortag": [
        "2112131",
        "1099364961"
      ],
      "lt_id_sptag": [
        "-154622774",
        "891390002",
        "82870",
        "126637389",
        "-326078627",
        "-1783086774",
        "1911583362"
      ]
    },
    {
      "hc_lt_id_alb": "-365719382",
      "hc_lt_id_nortag": "2103250494",
      "hc_lt_id_sptag": "1590530831",
      "id_img": "Original_836972_crop2608_-437936135",
      "link_img": "UTb0sGqADnbLiHq9qhRMRkSRiLND0Tk7ctN8tpraiicflgjG1iYgxw2Bs6DKdEESYe/3cZtUfTKNVn1N2s+UMpVy4706IhQgSYlgwrgVRHU=",
      "thumb": "UTb0sGqADnbLiHq9qhRMRkSRiLND0Tk7ctN8tpraiicflgjG1iYgxw2Bs6DKdEESbzOSQLN+6GI2SYn1GEZ+GpVy4706IhQgSYlgwrgVRHU=",
      "lt_id_alb": [
        "68811063",
        "109656519"
      ],
      "list_id_nortag": [
        "80057615",
        "1099364961",
        "-303857400",
        "65203733",
        "79944435"
      ],
      "lt_id_sptag": [
        "-154622774",
        "891390002",
        "-326078627",
        "-1783086774",
        "1911583362"
      ]
    },
    {
      "hc_lt_id_alb": "433290349",
      "hc_lt_id_nortag": "1153877818",
      "hc_lt_id_sptag": "1325658248",
      "id_img": "MyTeenRomanticComedySNAFU_599322_crop2608_-384542742",
      "link_img": "UTb0sGqADnbLiHq9qhRMRkSRiLND0Tk7ctN8tpraiiepRX1KuYJza7z8GBDQ+5GIaxPmXj+NZHoLTZjPKtC7ipVy4706IhQgSYlgwrgVRHU=",
      "thumb": "UTb0sGqADnbLiHq9qhRMRkSRiLND0Tk7ctN8tpraiiepRX1KuYJza7z8GBDQ+5GIwh3RRL8vOGyicG+Qa5yMi5Vy4706IhQgSYlgwrgVRHU=",
      "lt_id_alb": [
        "-1741349685",
        "68811063"
      ],
      "list_id_nortag": [
        "1433810066",
        "1207255719",
        "2015789921",
        "1099364961"
      ],
      "lt_id_sptag": [
        "-154622774",
        "891390002",
        "-143120565",
        "-1364967268",
        "-326078627",
        "1439812287",
        "1439506876",
        "1911583362",
        "635218351"
      ]
    }
  ],
  "lt_nortag": [
    {
      "id_nortag": "-1361231934",
      "name_nortag": "Akame Akame Ga Kill",
      "total_img": 46
    },
    {
      "id_nortag": "-1769491654",
      "name_nortag": "Archer FateStay Night",
      "total_img": 21
    },
    {
      "id_nortag": "940301965",
      "name_nortag": "Asuna Yuuki",
      "total_img": 201
    },
    {
      "id_nortag": "67510",
      "name_nortag": "Cat",
      "total_img": 128
    },
    {
      "id_nortag": "65203733",
      "name_nortag": "Cloud",
      "total_img": 163
    },
    {
      "id_nortag": "2112131",
      "name_nortag": "Cute",
      "total_img": 61
    },
    {
      "id_nortag": "1182614953",
      "name_nortag": "Eren Yeager",
      "total_img": 294
    },
    {
      "id_nortag": "-890365842",
      "name_nortag": "Erza Scarlet",
      "total_img": 39
    },
    {
      "id_nortag": "2225266",
      "name_nortag": "Goku",
      "total_img": 321
    },
    {
      "id_nortag": "1433810066",
      "name_nortag": "Hachiman Hikigaya",
      "total_img": 9
    },
    {
      "id_nortag": "1862163858",
      "name_nortag": "Highschool Of The Dead",
      "total_img": 3
    },
    {
      "id_nortag": "-1185956769",
      "name_nortag": "Hinata Hyuga",
      "total_img": 54
    },
    {
      "id_nortag": "-958187632",
      "name_nortag": "Ichigo Kurosaki",
      "total_img": 201
    },
    {
      "id_nortag": "1684926246",
      "name_nortag": "Inori Yuzuriha",
      "total_img": 32
    },
    {
      "id_nortag": "1207255719",
      "name_nortag": "Iroha Isshiki",
      "total_img": 5
    },
    {
      "id_nortag": "1837763930",
      "name_nortag": "Itachi Uchiha",
      "total_img": 58
    },
    {
      "id_nortag": "115056883",
      "name_nortag": "Kanade Tachibana",
      "total_img": 216
    },
    {
      "id_nortag": "436735501",
      "name_nortag": "Kaori Kanzaki",
      "total_img": 5
    },
    {
      "id_nortag": "-1352771606",
      "name_nortag": "Kaori Miyazono",
      "total_img": 138
    },
    {
      "id_nortag": "-320799925",
      "name_nortag": "Kazuto Kirigaya",
      "total_img": 125
    },
    {
      "id_nortag": "-711817417",
      "name_nortag": "Ken Kaneki",
      "total_img": 255
    },
    {
      "id_nortag": "-61413949",
      "name_nortag": "Kirito Sword Art Online",
      "total_img": 206
    },
    {
      "id_nortag": "489708789",
      "name_nortag": "Korra The Legend Of Korra",
      "total_img": 11
    },
    {
      "id_nortag": "-114492302",
      "name_nortag": "Kousei Arima",
      "total_img": 59
    },
    {
      "id_nortag": "518491969",
      "name_nortag": "Kurisu Makise",
      "total_img": 38
    },
    {
      "id_nortag": "455752626",
      "name_nortag": "Kurome Akame Ga Kill",
      "total_img": 8
    },
    {
      "id_nortag": "1339700914",
      "name_nortag": "L Death Note",
      "total_img": 24
    },
    {
      "id_nortag": "-979079592",
      "name_nortag": "Levi Ackerman",
      "total_img": 232
    },
    {
      "id_nortag": "-148568472",
      "name_nortag": "Madara Uchiha",
      "total_img": 21
    },
    {
      "id_nortag": "-460280087",
      "name_nortag": "Masami Iwasawa",
      "total_img": 27
    },
    {
      "id_nortag": "-455869487",
      "name_nortag": "Mato Kuroi",
      "total_img": 19
    },
    {
      "id_nortag": "-759650044",
      "name_nortag": "Mikasa Ackerman",
      "total_img": 326
    },
    {
      "id_nortag": "1869358694",
      "name_nortag": "Minato Namikaze",
      "total_img": 43
    },
    {
      "id_nortag": "-1643022489",
      "name_nortag": "Monkey D Luffy",
      "total_img": 156
    },
    {
      "id_nortag": "154658675",
      "name_nortag": "Naruto Uzumaki",
      "total_img": 292
    },
    {
      "id_nortag": "-1873931185",
      "name_nortag": "Natsu Dragneel",
      "total_img": 117
    },
    {
      "id_nortag": "-540557569",
      "name_nortag": "Portgas D Ace",
      "total_img": 48
    },
    {
      "id_nortag": "-1278041944",
      "name_nortag": "Rin Tohsaka",
      "total_img": 36
    },
    {
      "id_nortag": "-455647535",
      "name_nortag": "Rock Lee",
      "total_img": 23
    },
    {
      "id_nortag": "-899970271",
      "name_nortag": "Ryuk Death Note",
      "total_img": 15
    },
    {
      "id_nortag": "-272046484",
      "name_nortag": "Saber Fate Series",
      "total_img": 218
    },
    {
      "id_nortag": "584016335",
      "name_nortag": "Sabo One Piece",
      "total_img": 25
    },
    {
      "id_nortag": "-1611763306",
      "name_nortag": "Sakura Haruno",
      "total_img": 93
    },
    {
      "id_nortag": "-285202530",
      "name_nortag": "Sasuke Uchiha",
      "total_img": 154
    },
    {
      "id_nortag": "-303857400",
      "name_nortag": "School Uniform",
      "total_img": 467
    },
    {
      "id_nortag": "-928006557",
      "name_nortag": "Shingeki No Kyojin",
      "total_img": 201
    },
    {
      "id_nortag": "-342064395",
      "name_nortag": "Shinichi Izumi",
      "total_img": 6
    },
    {
      "id_nortag": "554120321",
      "name_nortag": "Shino Asada",
      "total_img": 34
    },
    {
      "id_nortag": "-182895206",
      "name_nortag": "Shu Ouma",
      "total_img": 9
    },
    {
      "id_nortag": "-63719044",
      "name_nortag": "Sinon Sword Art Online",
      "total_img": 49
    },
    {
      "id_nortag": "79944435",
      "name_nortag": "Skirt",
      "total_img": 368
    },
    {
      "id_nortag": "80057615",
      "name_nortag": "Socks",
      "total_img": 28
    },
    {
      "id_nortag": "570659319",
      "name_nortag": "Tony Tony Chopper",
      "total_img": 59
    },
    {
      "id_nortag": "-339618269",
      "name_nortag": "Touka Kirishima",
      "total_img": 89
    },
    {
      "id_nortag": "1701816780",
      "name_nortag": "Trafalgar Law",
      "total_img": 26
    },
    {
      "id_nortag": "2015789921",
      "name_nortag": "Yui Yuigahama",
      "total_img": 24
    },
    {
      "id_nortag": "1099364961",
      "name_nortag": "Yukino Yukinoshita",
      "total_img": 30
    },
    {
      "id_nortag": "2115335358",
      "name_nortag": "Yuno Gasai",
      "total_img": 18
    },
    {
      "id_nortag": "-2066368222",
      "name_nortag": "Yuuki Konno",
      "total_img": 40
    }
  ],
  "lt_sptag": [
    {
      "id_sptag": "-1436512555",
      "key_sptag": "isDarkBlack",
      "name_sptag": "Dark Black",
      "total": 4051
    },
    {
      "id_sptag": "1600730941",
      "key_sptag": "isGirlCuteCool",
      "name_sptag": "Girls Cute Cool",
      "total": 31431
    },
    {
      "id_sptag": "-369654561",
      "key_sptag": "isGirlDarkAnime",
      "name_sptag": "Girls Dark",
      "total": 3468
    },
    {
      "id_sptag": "-1783086774",
      "key_sptag": "isGirlEyesBlackAnime",
      "name_sptag": "Girls Eyes Black",
      "total": 5810
    },
    {
      "id_sptag": "635218351",
      "key_sptag": "isGirlEyesBlueAnime",
      "name_sptag": "Girls Eyes Blue",
      "total": 25656
    },
    {
      "id_sptag": "-1782893951",
      "key_sptag": "isGirlEyesBrownAnime",
      "name_sptag": "Girls Eyes Brown",
      "total": 9376
    },
    {
      "id_sptag": "635372596",
      "key_sptag": "isGirlEyesGreyAnime",
      "name_sptag": "Girls Eyes Grey",
      "total": 2483
    },
    {
      "id_sptag": "936615491",
      "key_sptag": "isGirlEyesOrangeAnime",
      "name_sptag": "Girls Eyes Orange",
      "total": 3828
    },
    {
      "id_sptag": "635632331",
      "key_sptag": "isGirlEyesPinkAnime",
      "name_sptag": "Girls Eyes Pink",
      "total": 1874
    },
    {
      "id_sptag": "-1364967268",
      "key_sptag": "isGirlEyesRedAnime",
      "name_sptag": "Girls Eyes Red",
      "total": 12697
    },
    {
      "id_sptag": "1043155746",
      "key_sptag": "isGirlEyesSilvertAnime",
      "name_sptag": "Girls Eyes Silver",
      "total": 1109
    },
    {
      "id_sptag": "1129122964",
      "key_sptag": "isGirlEyesVioletAnime",
      "name_sptag": "Girls Eyes Violet",
      "total": 6410
    },
    {
      "id_sptag": "-1415763167",
      "key_sptag": "isGirlGlassesAnime",
      "name_sptag": "Girls Glasses",
      "total": 2385
    },
    {
      "id_sptag": "-154622774",
      "key_sptag": "isGirlHairBlackAnime",
      "name_sptag": "Girls Hair Black",
      "total": 16737
    },
    {
      "id_sptag": "-143534545",
      "key_sptag": "isGirlHairBlueAnime",
      "name_sptag": "Girls Hair Blue",
      "total": 9528
    },
    {
      "id_sptag": "-143528947",
      "key_sptag": "isGirlHairBrownAnime",
      "name_sptag": "Girls Hair Brow",
      "total": 13760
    },
    {
      "id_sptag": "-143380300",
      "key_sptag": "isGirlHairGreyAnime",
      "name_sptag": "Girls Hair Grey",
      "total": 9239
    },
    {
      "id_sptag": "-120608061",
      "key_sptag": "isGirlHairOrangeAnime",
      "name_sptag": "Girls Hair Orange",
      "total": 4128
    },
    {
      "id_sptag": "-143120565",
      "key_sptag": "isGirlHairPinkAnime",
      "name_sptag": "Girls Hair Pink",
      "total": 5690
    },
    {
      "id_sptag": "-143162340",
      "key_sptag": "isGirlHairRedAnime",
      "name_sptag": "Girls Hair Red",
      "total": 3081
    },
    {
      "id_sptag": "71899412",
      "key_sptag": "isGirlHairVioletAnime",
      "name_sptag": "Girls Hair Violet",
      "total": 2650
    },
    {
      "id_sptag": "154003721",
      "key_sptag": "isGirlHairYellowAnime",
      "name_sptag": "Girls Hair Yellow",
      "total": 12651
    },
    {
      "id_sptag": "-369535327",
      "key_sptag": "isGirlHatsAnime",
      "name_sptag": "Girls Hats",
      "total": 11965
    },
    {
      "id_sptag": "-326078627",
      "key_sptag": "isGirlLongHairAnime",
      "name_sptag": "Girls Long Hair",
      "total": 47407
    },
    {
      "id_sptag": "-369386728",
      "key_sptag": "isGirlMaidAnime",
      "name_sptag": "Girls Maid",
      "total": 2625
    },
    {
      "id_sptag": "1434519004",
      "key_sptag": "isGirMusicAnime",
      "name_sptag": "Girls Music",
      "total": 1611
    },
    {
      "id_sptag": "126637389",
      "key_sptag": "isGirlSadAnime",
      "name_sptag": "Girls Sad",
      "total": 10506
    },
    {
      "id_sptag": "1439506876",
      "key_sptag": "isGirlScarfAnime",
      "name_sptag": "Girls Scarf",
      "total": 3306
    },
    {
      "id_sptag": "-2139213873",
      "key_sptag": "isGirlShortHairAnime",
      "name_sptag": "Girls Short Hair",
      "total": 23769
    },
    {
      "id_sptag": "1439812287",
      "key_sptag": "isGirlSmileAnime",
      "name_sptag": "Girls Smile",
      "total": 24284
    },
    {
      "id_sptag": "891390002",
      "key_sptag": "isGirlStudentAnime",
      "name_sptag": "Girls Student",
      "total": 16308
    },
    {
      "id_sptag": "1911583362",
      "key_sptag": "isGirlTieBowsAnime",
      "name_sptag": "Girls Tie Bows",
      "total": 61257
    },
    {
      "id_sptag": "-1811357781",
      "key_sptag": "isGirlUniformAnime",
      "name_sptag": "Girls Uniform",
      "total": 16929
    },
    {
      "id_sptag": "-1743477818",
      "key_sptag": "isGirlWaterRainAnime",
      "name_sptag": "Girls Water Rain",
      "total": 2954
    },
    {
      "id_sptag": "82870",
      "key_sptag": "isSad",
      "name_sptag": "Sad",
      "total": 12057
    }
  ]
}